{
  "id": "ultimateforge-journeyforge",
  "title": "UltimateForge : JourneyForge",
  "description": "Moteur narratif et générateur d'événements de voyage, lisant dynamiquement la carte, le climat et l'aura des villes.",
  "version": "1.0.0",
  "compatibility": {
    "minimum": "12",
    "verified": "13"
  },
  "authors": [
    {
      "name": "Ours_glace"
    }
  ],
  "languages": [
    {
      "lang": "fr",
      "name": "Français",
      "path": "lang/fr.json"
    },
    {
      "lang": "en",
      "name": "English",
      "path": "lang/en.json"
    }
  ],
  "esmodules": [
    "scripts/apps/ultimateforge-journeyforge.mjs"
  ],
  "relationships": {
    "requires": [
      {
        "id": "ultimateforge-core",
        "type": "module"
      },
      {
        "id": "ultimateforge-hexforge",
        "type": "module"
      },
      {
        "id": "ultimateforge-cityforge",
        "type": "module"
      }
    ]
  },
  
  "url": "https://avantis.world",
  "manifest": "https://raw.githubusercontent.com/gilshyran/Projet_UltimateForge/refs/heads/main/ultimateforge-journeyforge/module.json",
  "download": "https://github.com/gilshyran/Projet_UltimateForge/releases/download/v1.0.0/ultimateforge-journeyforge.zip"
}